src/__init__.py
src/audio/__init__.py
src/audio/recorder/__init__.py
src/audio/whisper/__init__.py
src/chat/__init__.py
src/client/__init__.py
src/client/vrchat_osc.py
src/main.py
tsukiyo-0.1.0.dist-info/LICENSE
tsukiyo-0.1.0.dist-info/METADATA
tsukiyo-0.1.0.dist-info/WHEEL
tsukiyo-0.1.0.dist-info/entry_points.txt
tsukiyo-0.1.0.dist-info/RECORD
